{"cameraMode":{"drawMode":0,"name":"Shaded","section":"Shading Mode"},"sceneLighting":true,"audioPlay":false,"sceneViewState":{"m_AlwaysRefresh":false,"showFog":true,"showSkybox":true,"showFlares":true,"showImageEffects":true,"showParticleSystems":true,"showVisualEffectGraphs":true,"m_FxEnabled":true},"in2DMode":false,"pivot":{"x":0.02582213282585144,"y":9.347356796264649,"z":-7.456853866577148},"rotation":{"x":-0.44235149025917055,"y":-0.009111069142818451,"z":0.0008635346894152463,"w":-0.8985284566879273},"size":0.26928868889808657,"orthographic":false}